<?xml version="1.0" encoding="UTF-8" ?>
<!DOCTYPE mapper PUBLIC "-//mybatis.org//DTD Mapper 3.0//EN" "http://mybatis.org/dtd/mybatis-3-mapper.dtd" >
<mapper namespace="com.greenplatform.dao.TGreenZzZjzzmxMapper" >
  <resultMap id="BaseResultMap" type="com.greenplatform.model.TGreenZzZjzzmx" >
    <!--
      WARNING - @mbggenerated
      This element is automatically generated by MyBatis Generator, do not modify.
    -->
    <id column="c_lsh" property="cLsh" jdbcType="VARCHAR" />
    <result column="c_userid" property="cUserid" jdbcType="VARCHAR" />
    <result column="c_spbh" property="cSpbh" jdbcType="VARCHAR" />
    <result column="c_zjyy" property="cZjyy" jdbcType="VARCHAR" />
    <result column="d_zjsj" property="dZjsj" jdbcType="TIMESTAMP" />
    <result column="c_kjz" property="cKjz" jdbcType="VARCHAR" />
    <result column="c_sfjz" property="cSfjz" jdbcType="VARCHAR" />
    <result column="d_jzsj" property="dJzsj" jdbcType="TIMESTAMP" />
    <result column="c_bz" property="cBz" jdbcType="VARCHAR" />
    <result column="c_zt" property="cZt" jdbcType="VARCHAR" />
    <result column="c_cjuser" property="cCjuser" jdbcType="VARCHAR" />
    <result column="d_cjsj" property="dCjsj" jdbcType="TIMESTAMP" />
    <result column="c_xguser" property="cXguser" jdbcType="VARCHAR" />
    <result column="d_xgsj" property="dXgsj" jdbcType="TIMESTAMP" />
  </resultMap>
  <delete id="deleteByPrimaryKey" parameterType="java.lang.String" >
    <!--
      WARNING - @mbggenerated
      This element is automatically generated by MyBatis Generator, do not modify.
    -->
    delete from t_green_zz_zjzzmx
    where c_lsh = #{cLsh,jdbcType=VARCHAR}
  </delete>
  <insert id="insert" parameterType="com.greenplatform.model.TGreenZzZjzzmx" >
    <!--
      WARNING - @mbggenerated
      This element is automatically generated by MyBatis Generator, do not modify.
    -->
    insert into t_green_zz_zjzzmx (c_lsh, c_userid, c_spbh, 
      c_zjyy, d_zjsj, c_kjz, 
      c_sfjz, d_jzsj, c_bz, 
      c_zt, c_cjuser, d_cjsj, 
      c_xguser, d_xgsj)
    values (#{cLsh,jdbcType=VARCHAR}, #{cUserid,jdbcType=VARCHAR}, #{cSpbh,jdbcType=VARCHAR}, 
      #{cZjyy,jdbcType=VARCHAR}, #{dZjsj,jdbcType=TIMESTAMP}, #{cKjz,jdbcType=VARCHAR}, 
      #{cSfjz,jdbcType=VARCHAR}, #{dJzsj,jdbcType=TIMESTAMP}, #{cBz,jdbcType=VARCHAR}, 
      #{cZt,jdbcType=VARCHAR}, #{cCjuser,jdbcType=VARCHAR}, #{dCjsj,jdbcType=TIMESTAMP}, 
      #{cXguser,jdbcType=VARCHAR}, #{dXgsj,jdbcType=TIMESTAMP})
  </insert>
  <update id="updateByPrimaryKey" parameterType="com.greenplatform.model.TGreenZzZjzzmx" >
    <!--
      WARNING - @mbggenerated
      This element is automatically generated by MyBatis Generator, do not modify.
    -->
    update t_green_zz_zjzzmx
    set c_userid = #{cUserid,jdbcType=VARCHAR},
      c_spbh = #{cSpbh,jdbcType=VARCHAR},
      c_zjyy = #{cZjyy,jdbcType=VARCHAR},
      d_zjsj = #{dZjsj,jdbcType=TIMESTAMP},
      c_kjz = #{cKjz,jdbcType=VARCHAR},
      c_sfjz = #{cSfjz,jdbcType=VARCHAR},
      d_jzsj = #{dJzsj,jdbcType=TIMESTAMP},
      c_bz = #{cBz,jdbcType=VARCHAR},
      c_zt = #{cZt,jdbcType=VARCHAR},
      c_cjuser = #{cCjuser,jdbcType=VARCHAR},
      d_cjsj = #{dCjsj,jdbcType=TIMESTAMP},
      c_xguser = #{cXguser,jdbcType=VARCHAR},
      d_xgsj = #{dXgsj,jdbcType=TIMESTAMP}
    where c_lsh = #{cLsh,jdbcType=VARCHAR}
  </update>
  <select id="selectByPrimaryKey" resultMap="BaseResultMap" parameterType="java.lang.String" >
    <!--
      WARNING - @mbggenerated
      This element is automatically generated by MyBatis Generator, do not modify.
    -->
    select c_lsh, c_userid, c_spbh, c_zjyy, d_zjsj, c_kjz, c_sfjz, d_jzsj, c_bz, c_zt, 
    c_cjuser, d_cjsj, c_xguser, d_xgsj
    from t_green_zz_zjzzmx
    where c_lsh = #{cLsh,jdbcType=VARCHAR}
  </select>
  <select id="selectAll" resultMap="BaseResultMap" >
    <!--
      WARNING - @mbggenerated
      This element is automatically generated by MyBatis Generator, do not modify.
    -->
    select c_lsh, c_userid, c_spbh, c_zjyy, d_zjsj, c_kjz, c_sfjz, d_jzsj, c_bz, c_zt, 
    c_cjuser, d_cjsj, c_xguser, d_xgsj
    from t_green_zz_zjzzmx
  </select>


  <select id="selectTGreenZzZjzzmx" parameterType="com.greenplatform.model.TGreenZzZjzzmx" resultMap="BaseResultMap">
    SELECT T.* FROM t_green_zz_zjzzmx T WHERE 1=1
    <if test='cLsh!=null and cLsh!=""'>
      AND T.c_lsh = #{cLsh}
    </if>
    <if test='cUserid!=null and cUserid!=""'>
      AND T.c_userid = #{cUserid}
    </if>
    <if test='cSpbh!=null and cSpbh!=""'>
      AND T.c_spbh = #{cSpbh}
    </if>
    <if test='cZjyy!=null and cZjyy!=""'>
      AND T.c_zjyy = #{cZjyy}
    </if>
    <if test='dZjsj!=null and dZjsj!=""'>
      AND T.d_zjsj = #{dZjsj}
    </if>
    <if test='cKjz!=null and cKjz!=""'>
      AND T.c_kjz = #{cKjz}
    </if>
    <if test='cSfjz!=null and cSfjz!=""'>
      AND T.c_sfjz = #{cSfjz}
    </if>
    <if test='dJzsj!=null and dJzsj!=""'>
      AND T.d_jzsj = #{dJzsj}
    </if>
    <if test='cZt!=null and cZt!=""'>
      AND T.c_zt = #{cZt}
    </if>
    <if test='cCjuser!=null and cCjuser!=""'>
      AND T.c_cjuser = #{cCjuser}
    </if>
    ORDER BY T.d_zjsj DESC
  </select>
</mapper>